{
  "_generic": {
    "defaultPackage": "bjyoungblood/bjy-authorize",
    "location": "",
    "packages": {
      "bjyoungblood/bjy-authorize": "1.5.0-beta1"
    },
    "sourcesAggregatedHash": null,
    "subsystem": "php"
  },
  "_subsystem": {
    "composerPluginApiSemver": {},
    "phpExtensions": [
      "tokenizer",
      "curl",
      "ctype",
      "dom",
      "json",
      "pcre",
      "reflection",
      "spl",
      "simplexml"
    ],
    "phpSemver": ">=5.3.3"
  },
  "cyclicDependencies": {},
  "dependencies": {
    "bjyoungblood/bjy-authorize": {
      "1.5.0-beta1": [
        [ "phpunit/phpunit", "3.7.38" ],
        [ "satooshi/php-coveralls", "v0.7.1" ],
        [ "squizlabs/php_codesniffer", "1.4.8" ],
        [ "zendframework/zend-cache", "2.8.3" ],
        [ "zendframework/zend-developer-tools", "0.0.2" ],
        [ "zendframework/zend-http", "2.8.4" ],
        [ "zendframework/zend-mvc", "2.7.15" ],
        [ "zendframework/zend-servicemanager", "2.7.11" ]
      ]
    },
    "phpunit/php-code-coverage": {
      "1.2.18": [
        [ "phpunit/php-text-template", "1.2.1" ],
        [ "phpunit/php-token-stream", "1.2.2" ]
      ]
    },
    "phpunit/phpunit": {
      "3.7.38": [
        [ "phpunit/php-code-coverage", "1.2.18" ],
        [ "phpunit/php-text-template", "1.2.1" ],
        [ "symfony/polyfill-ctype", "dev-main" ]
      ]
    },
    "satooshi/php-coveralls": {
      "v0.7.1": [
        [ "psr/log", "1.1.4" ]
      ]
    },
    "zendframework/zend-cache": {
      "2.8.3": [
        [ "psr/cache", "1.0.1" ],
        [ "psr/simple-cache", "1.0.1" ],
        [ "zendframework/zend-servicemanager", "2.7.11" ]
      ]
    },
    "zendframework/zend-developer-tools": {
      "0.0.2": [
        [ "zendframework/zend-mvc", "2.7.15" ],
        [ "zendframework/zend-servicemanager", "2.7.11" ]
      ]
    },
    "zendframework/zend-form": {
      "2.13.0": [
        [ "zendframework/zend-hydrator", "1.1.0" ]
      ]
    },
    "zendframework/zend-http": {
      "2.8.4": [
        [ "zendframework/zend-validator", "2.11.1" ]
      ]
    },
    "zendframework/zend-mvc": {
      "2.7.15": [
        [ "container-interop/container-interop", "1.2.0" ],
        [ "zendframework/zend-console", "2.7.0" ],
        [ "zendframework/zend-form", "2.13.0" ],
        [ "zendframework/zend-hydrator", "1.1.0" ],
        [ "zendframework/zend-psr7bridge", "0.2.2" ],
        [ "zendframework/zend-servicemanager", "2.7.11" ]
      ]
    },
    "zendframework/zend-psr7bridge": {
      "0.2.2": [
        [ "zendframework/zend-http", "2.8.4" ]
      ]
    },
    "zendframework/zend-servicemanager": {
      "2.7.11": [
        [ "container-interop/container-interop", "1.2.0" ]
      ]
    },
    "zendframework/zend-validator": {
      "2.11.1": [
        [ "container-interop/container-interop", "1.2.0" ]
      ]
    }
  },
  "sources": {
    "bjyoungblood/bjy-authorize": {
      "1.5.0-beta1": {
        "rev": "8214a324c3307f6675e8c38228e4b304ceb29fc8",
        "type": "git",
        "url": "https://github.com/bjyoungblood/BjyAuthorize.git"
      }
    },
    "container-interop/container-interop": {
      "1.2.0": {
        "rev": "79cbf1341c22ec75643d841642dd5d6acd83bdb8",
        "type": "git",
        "url": "https://github.com/container-interop/container-interop.git"
      }
    },
    "phpunit/php-code-coverage": {
      "1.2.18": {
        "rev": "fe2466802556d3fe4e4d1d58ffd3ccfd0a19be0b",
        "type": "git",
        "url": "https://github.com/sebastianbergmann/php-code-coverage.git"
      }
    },
    "phpunit/php-text-template": {
      "1.2.1": {
        "rev": "31f8b717e51d9a2afca6c9f046f5d69fc27c8686",
        "type": "git",
        "url": "https://github.com/sebastianbergmann/php-text-template.git"
      }
    },
    "phpunit/php-token-stream": {
      "1.2.2": {
        "rev": "ad4e1e23ae01b483c16f600ff1bebec184588e32",
        "type": "git",
        "url": "https://github.com/sebastianbergmann/php-token-stream.git"
      }
    },
    "phpunit/phpunit": {
      "3.7.38": {
        "rev": "38709dc22d519a3d1be46849868aa2ddf822bcf6",
        "type": "git",
        "url": "https://github.com/sebastianbergmann/phpunit.git"
      }
    },
    "psr/cache": {
      "1.0.1": {
        "rev": "d11b50ad223250cf17b86e38383413f5a6764bf8",
        "type": "git",
        "url": "https://github.com/php-fig/cache.git"
      }
    },
    "psr/log": {
      "1.1.4": {
        "rev": "d49695b909c3b7628b6289db5479a1c204601f11",
        "type": "git",
        "url": "https://github.com/php-fig/log.git"
      }
    },
    "psr/simple-cache": {
      "1.0.1": {
        "rev": "408d5eafb83c57f6365a3ca330ff23aa4a5fa39b",
        "type": "git",
        "url": "https://github.com/php-fig/simple-cache.git"
      }
    },
    "satooshi/php-coveralls": {
      "v0.7.1": {
        "rev": "01793ce60f1e259592ac3cb7c3fc183209800127",
        "type": "git",
        "url": "https://github.com/satooshi/php-coveralls.git"
      }
    },
    "squizlabs/php_codesniffer": {
      "1.4.8": {
        "rev": "d26daa8096ad2c8758677f0352597f8cda4722e0",
        "type": "git",
        "url": "https://github.com/squizlabs/PHP_CodeSniffer.git"
      }
    },
    "symfony/polyfill-ctype": {
      "dev-main": {
        "rev": "6fd1b9a79f6e3cf65f9e679b23af304cd9e010d4",
        "type": "git",
        "url": "https://github.com/symfony/polyfill-ctype.git"
      }
    },
    "zendframework/zend-cache": {
      "2.8.3": {
        "rev": "edde41f1ee5c28e01701a032f434d03751b65df4",
        "type": "git",
        "url": "https://github.com/zendframework/zend-cache.git"
      }
    },
    "zendframework/zend-console": {
      "2.7.0": {
        "rev": "e8aa08da83de3d265256c40ba45cd649115f0e18",
        "type": "git",
        "url": "https://github.com/zendframework/zend-console.git"
      }
    },
    "zendframework/zend-developer-tools": {
      "0.0.2": {
        "rev": "9b9311311fdb562494f89e62eb4649d687b58364",
        "type": "git",
        "url": "https://github.com/zendframework/ZendDeveloperTools.git"
      }
    },
    "zendframework/zend-form": {
      "2.13.0": {
        "rev": "c713a12ccbd43148b71c9339e171ca11e3f8a1da",
        "type": "git",
        "url": "https://github.com/zendframework/zend-form.git"
      }
    },
    "zendframework/zend-http": {
      "2.8.4": {
        "rev": "d160aedc096be230af0fe9c31151b2b33ad4e807",
        "type": "git",
        "url": "https://github.com/zendframework/zend-http.git"
      }
    },
    "zendframework/zend-hydrator": {
      "1.1.0": {
        "rev": "22652e1661a5a10b3f564cf7824a2206cf5a4a65",
        "type": "git",
        "url": "https://github.com/zendframework/zend-hydrator.git"
      }
    },
    "zendframework/zend-mvc": {
      "2.7.15": {
        "rev": "a8d45689d37a9e4ff4b75ea0b7478fa3d4f9c089",
        "type": "git",
        "url": "https://github.com/zendframework/zend-mvc.git"
      }
    },
    "zendframework/zend-psr7bridge": {
      "0.2.2": {
        "rev": "86c0b53b0c6381391c4add4a93a56e51d5c74605",
        "type": "git",
        "url": "https://github.com/zendframework/zend-psr7bridge.git"
      }
    },
    "zendframework/zend-servicemanager": {
      "2.7.11": {
        "rev": "99ec9ed5d0f15aed9876433c74c2709eb933d4c7",
        "type": "git",
        "url": "https://github.com/zendframework/zend-servicemanager.git"
      }
    },
    "zendframework/zend-validator": {
      "2.11.1": {
        "rev": "3c28dfe4e5951ba38059cea895244d9d206190b3",
        "type": "git",
        "url": "https://github.com/zendframework/zend-validator.git"
      }
    }
  }
}
