{
  "_generic": {
    "defaultPackage": "symfony/http-kernel",
    "location": "",
    "packages": {
      "symfony/http-kernel": "v6.1.4"
    },
    "sourcesAggregatedHash": null,
    "subsystem": "php"
  },
  "_subsystem": {
    "phpExtensions": [
      "ctype",
      "dom",
      "libxml"
    ],
    "phpSemver": ">=8.1"
  },
  "cyclicDependencies": {},
  "dependencies": {},
  "sources": {
    "symfony/http-kernel": {
      "v6.1.4": {
        "rev": "2144c53a278254af57fa1e6f71427be656fab6f4",
        "type": "git",
        "url": "https://github.com/symfony/http-kernel.git"
      }
    }
  }
}
