{
  "_generic": {
    "defaultPackage": "coduo/phpspec-data-provider-extension",
    "location": "",
    "packages": {
      "coduo/phpspec-data-provider-extension": "1.0.3"
    },
    "sourcesAggregatedHash": null,
    "subsystem": "php"
  },
  "_subsystem": {
    "composerPluginApiSemver": {},
    "noDev": false,
    "phpExtensions": [
      "filter",
      "tokenizer",
      "ctype",
      "mbstring"
    ],
    "phpSemver": ">=5.4.0"
  },
  "cyclicDependencies": {},
  "dependencies": {
    "behat/behat": {
      "v3.0.15": [
        [ "behat/gherkin", "v4.9.0" ],
        [ "behat/transliterator", "v1.5.0" ],
        [ "symfony/class-loader", "v2.8.52" ],
        [ "symfony/config", "v2.8.52" ],
        [ "symfony/console", "v2.3.42" ],
        [ "symfony/dependency-injection", "v2.8.52" ],
        [ "symfony/event-dispatcher", "v2.8.52" ],
        [ "symfony/polyfill-mbstring", "v1.27.0" ],
        [ "symfony/translation", "v2.8.52" ],
        [ "symfony/yaml", "v2.8.52" ]
      ]
    },
    "bossa/phpspec2-expect": {
      "1.0.3": [
        [ "phpspec/phpspec", "2.5.8" ]
      ]
    },
    "coduo/phpspec-data-provider-extension": {
      "1.0.3": [
        [ "behat/behat", "v3.0.15" ],
        [ "bossa/phpspec2-expect", "1.0.3" ],
        [ "phpspec/phpspec", "2.5.8" ],
        [ "symfony/console", "v2.3.42" ],
        [ "symfony/filesystem", "v2.8.52" ],
        [ "symfony/process", "v2.8.52" ]
      ]
    },
    "phpdocumentor/reflection-docblock": {
      "5.3.0": [
        [ "phpdocumentor/reflection-common", "2.2.0" ],
        [ "phpdocumentor/type-resolver", "1.6.2" ],
        [ "webmozart/assert", "1.11.0" ]
      ]
    },
    "phpdocumentor/type-resolver": {
      "1.6.2": [
        [ "phpdocumentor/reflection-common", "2.2.0" ]
      ]
    },
    "phpspec/phpspec": {
      "2.5.8": [
        [ "doctrine/instantiator", "1.4.1" ],
        [ "phpspec/php-diff", "v1.0.2" ],
        [ "phpspec/prophecy", "v1.15.0" ],
        [ "sebastian/exporter", "3.1.5" ],
        [ "symfony/console", "v2.3.42" ],
        [ "symfony/event-dispatcher", "v2.8.52" ],
        [ "symfony/finder", "v3.4.47" ],
        [ "symfony/process", "v2.8.52" ],
        [ "symfony/yaml", "v2.8.52" ]
      ]
    },
    "phpspec/prophecy": {
      "v1.15.0": [
        [ "doctrine/instantiator", "1.4.1" ],
        [ "phpdocumentor/reflection-docblock", "5.3.0" ],
        [ "sebastian/comparator", "3.0.5" ],
        [ "sebastian/recursion-context", "3.0.1" ]
      ]
    },
    "sebastian/comparator": {
      "3.0.5": [
        [ "sebastian/diff", "3.0.3" ],
        [ "sebastian/exporter", "3.1.5" ]
      ]
    },
    "sebastian/exporter": {
      "3.1.5": [
        [ "sebastian/recursion-context", "3.0.1" ]
      ]
    },
    "symfony/class-loader": {
      "v2.8.52": [
        [ "symfony/polyfill-apcu", "v1.27.0" ]
      ]
    },
    "symfony/config": {
      "v2.8.52": [
        [ "symfony/filesystem", "v2.8.52" ],
        [ "symfony/polyfill-ctype", "v1.27.0" ]
      ]
    },
    "symfony/filesystem": {
      "v2.8.52": [
        [ "symfony/polyfill-ctype", "v1.27.0" ]
      ]
    },
    "symfony/translation": {
      "v2.8.52": [
        [ "symfony/polyfill-mbstring", "v1.27.0" ]
      ]
    },
    "symfony/yaml": {
      "v2.8.52": [
        [ "symfony/polyfill-ctype", "v1.27.0" ]
      ]
    },
    "webmozart/assert": {
      "1.11.0": [
        [ "symfony/polyfill-ctype", "v1.27.0" ]
      ]
    }
  },
  "sources": {
    "behat/behat": {
      "v3.0.15": {
        "rev": "b35ae3d45332d80c532af69cc36f780a9397a996",
        "submodules": false,
        "type": "git",
        "url": "https://github.com/Behat/Behat.git"
      }
    },
    "behat/gherkin": {
      "v4.9.0": {
        "rev": "0bc8d1e30e96183e4f36db9dc79caead300beff4",
        "submodules": false,
        "type": "git",
        "url": "https://github.com/Behat/Gherkin.git"
      }
    },
    "behat/transliterator": {
      "v1.5.0": {
        "rev": "baac5873bac3749887d28ab68e2f74db3a4408af",
        "submodules": false,
        "type": "git",
        "url": "https://github.com/Behat/Transliterator.git"
      }
    },
    "bossa/phpspec2-expect": {
      "1.0.3": {
        "rev": "f3a80b7fa743b8a1078a7e320bd3e8b8b6283780",
        "submodules": false,
        "type": "git",
        "url": "https://github.com/BossaConsulting/phpspec2-expect.git"
      }
    },
    "coduo/phpspec-data-provider-extension": {
      "1.0.3": {
        "rev": "b8d5c8594fec5ab2d7000bc31822a411bcd45146",
        "type": "git",
        "url": "https://github.com/coduo/phpspec-data-provider-extension.git"
      }
    },
    "doctrine/instantiator": {
      "1.4.1": {
        "rev": "10dcfce151b967d20fde1b34ae6640712c3891bc",
        "submodules": false,
        "type": "git",
        "url": "https://github.com/doctrine/instantiator.git"
      }
    },
    "phpdocumentor/reflection-common": {
      "2.2.0": {
        "rev": "1d01c49d4ed62f25aa84a747ad35d5a16924662b",
        "submodules": false,
        "type": "git",
        "url": "https://github.com/phpDocumentor/ReflectionCommon.git"
      }
    },
    "phpdocumentor/reflection-docblock": {
      "5.3.0": {
        "rev": "622548b623e81ca6d78b721c5e029f4ce664f170",
        "submodules": false,
        "type": "git",
        "url": "https://github.com/phpDocumentor/ReflectionDocBlock.git"
      }
    },
    "phpdocumentor/type-resolver": {
      "1.6.2": {
        "rev": "48f445a408c131e38cab1c235aa6d2bb7a0bb20d",
        "submodules": false,
        "type": "git",
        "url": "https://github.com/phpDocumentor/TypeResolver.git"
      }
    },
    "phpspec/php-diff": {
      "v1.0.2": {
        "rev": "30e103d19519fe678ae64a60d77884ef3d71b28a",
        "submodules": false,
        "type": "git",
        "url": "https://github.com/phpspec/php-diff.git"
      }
    },
    "phpspec/phpspec": {
      "2.5.8": {
        "rev": "d8a153dcb52f929b448c0bf2cc19c7388951adb1",
        "submodules": false,
        "type": "git",
        "url": "https://github.com/phpspec/phpspec.git"
      }
    },
    "phpspec/prophecy": {
      "v1.15.0": {
        "rev": "bbcd7380b0ebf3961ee21409db7b38bc31d69a13",
        "submodules": false,
        "type": "git",
        "url": "https://github.com/phpspec/prophecy.git"
      }
    },
    "sebastian/comparator": {
      "3.0.5": {
        "rev": "1dc7ceb4a24aede938c7af2a9ed1de09609ca770",
        "submodules": false,
        "type": "git",
        "url": "https://github.com/sebastianbergmann/comparator.git"
      }
    },
    "sebastian/diff": {
      "3.0.3": {
        "rev": "14f72dd46eaf2f2293cbe79c93cc0bc43161a211",
        "submodules": false,
        "type": "git",
        "url": "https://github.com/sebastianbergmann/diff.git"
      }
    },
    "sebastian/exporter": {
      "3.1.5": {
        "rev": "73a9676f2833b9a7c36968f9d882589cd75511e6",
        "submodules": false,
        "type": "git",
        "url": "https://github.com/sebastianbergmann/exporter.git"
      }
    },
    "sebastian/recursion-context": {
      "3.0.1": {
        "rev": "367dcba38d6e1977be014dc4b22f47a484dac7fb",
        "submodules": false,
        "type": "git",
        "url": "https://github.com/sebastianbergmann/recursion-context.git"
      }
    },
    "symfony/class-loader": {
      "v2.8.52": {
        "rev": "8194721a1e2768cfb95079581889c41eec7a5959",
        "submodules": false,
        "type": "git",
        "url": "https://github.com/symfony/class-loader.git"
      }
    },
    "symfony/config": {
      "v2.8.52": {
        "rev": "7dd5f5040dc04c118d057fb5886563963eb70011",
        "submodules": false,
        "type": "git",
        "url": "https://github.com/symfony/config.git"
      }
    },
    "symfony/console": {
      "v2.3.42": {
        "rev": "20c12c6d6c5a087a66d4e77999451713a92a3507",
        "submodules": false,
        "type": "git",
        "url": "https://github.com/symfony/console.git"
      }
    },
    "symfony/dependency-injection": {
      "v2.8.52": {
        "rev": "c306198fee8f872a8f5f031e6e4f6f83086992d8",
        "submodules": false,
        "type": "git",
        "url": "https://github.com/symfony/dependency-injection.git"
      }
    },
    "symfony/event-dispatcher": {
      "v2.8.52": {
        "rev": "a77e974a5fecb4398833b0709210e3d5e334ffb0",
        "submodules": false,
        "type": "git",
        "url": "https://github.com/symfony/event-dispatcher.git"
      }
    },
    "symfony/filesystem": {
      "v2.8.52": {
        "rev": "7ae46872dad09dffb7fe1e93a0937097339d0080",
        "submodules": false,
        "type": "git",
        "url": "https://github.com/symfony/filesystem.git"
      }
    },
    "symfony/finder": {
      "v3.4.47": {
        "rev": "b6b6ad3db3edb1b4b1c1896b1975fb684994de6e",
        "submodules": false,
        "type": "git",
        "url": "https://github.com/symfony/finder.git"
      }
    },
    "symfony/polyfill-apcu": {
      "v1.27.0": {
        "rev": "6e7f6ed2168779a2b3927e606a9768860a8bdfa0",
        "submodules": false,
        "type": "git",
        "url": "https://github.com/symfony/polyfill-apcu.git"
      }
    },
    "symfony/polyfill-ctype": {
      "v1.27.0": {
        "rev": "5bbc823adecdae860bb64756d639ecfec17b050a",
        "submodules": false,
        "type": "git",
        "url": "https://github.com/symfony/polyfill-ctype.git"
      }
    },
    "symfony/polyfill-mbstring": {
      "v1.27.0": {
        "rev": "8ad114f6b39e2c98a8b0e3bd907732c207c2b534",
        "submodules": false,
        "type": "git",
        "url": "https://github.com/symfony/polyfill-mbstring.git"
      }
    },
    "symfony/process": {
      "v2.8.52": {
        "rev": "c3591a09c78639822b0b290d44edb69bf9f05dc8",
        "submodules": false,
        "type": "git",
        "url": "https://github.com/symfony/process.git"
      }
    },
    "symfony/translation": {
      "v2.8.52": {
        "rev": "fc58c2a19e56c29f5ba2736ec40d0119a0de2089",
        "submodules": false,
        "type": "git",
        "url": "https://github.com/symfony/translation.git"
      }
    },
    "symfony/yaml": {
      "v2.8.52": {
        "rev": "02c1859112aa779d9ab394ae4f3381911d84052b",
        "submodules": false,
        "type": "git",
        "url": "https://github.com/symfony/yaml.git"
      }
    },
    "webmozart/assert": {
      "1.11.0": {
        "rev": "11cb2199493b2f8a3b53e7f19068fc6aac760991",
        "submodules": false,
        "type": "git",
        "url": "https://github.com/webmozarts/assert.git"
      }
    }
  }
}
