{
  "_generic": {
    "defaultPackage": "symfony/class-loader",
    "location": "",
    "packages": {
      "symfony/class-loader": "v3.4.46"
    },
    "sourcesAggregatedHash": null,
    "subsystem": "php"
  },
  "_subsystem": {
    "phpExtensions": [],
    "phpPackageType": {
      "symfony/class-loader@v3.4.46": "library",
      "symfony/finder@4.4.x-dev": "library",
      "symfony/polyfill-apcu@dev-main": "library",
      "symfony/polyfill-php80@dev-main": "library"
    },
    "phpSemver": "^5.5.9|>=7.0.8"
  },
  "cyclicDependencies": {},
  "dependencies": {},
  "sources": {
    "symfony/class-loader": {
      "v3.4.46": {
        "rev": "a22265a9f3511c0212bf79f54910ca5a77c0e92c",
        "type": "git",
        "url": "https://github.com/symfony/class-loader.git"
      }
    }
  }
}
